andonapp/__init__.py
andonapp/andon_client.py
andonapp/exceptions.py
andonapp-1.0.0.dist-info/DESCRIPTION.rst
andonapp-1.0.0.dist-info/METADATA
andonapp-1.0.0.dist-info/RECORD
andonapp-1.0.0.dist-info/WHEEL
andonapp-1.0.0.dist-info/metadata.json
andonapp-1.0.0.dist-info/top_level.txt
